insightlab/Insight.py
insightlab/InsightObjects.py
insightlab-0.4.dist-info/METADATA
insightlab-0.4.dist-info/WHEEL
insightlab-0.4.dist-info/top_level.txt
insightlab-0.4.dist-info/RECORD
